git_security_scanner-0.1.4.dist-info/licenses/LICENSE
security_scanner/__init__.py
security_scanner/cache.py
security_scanner/cli.py
security_scanner/config.py
security_scanner/export.py
security_scanner/patterns.py
security_scanner/py.typed
security_scanner/scanner.py
security_scanner/utils.py
git_security_scanner-0.1.4.dist-info/METADATA
git_security_scanner-0.1.4.dist-info/WHEEL
git_security_scanner-0.1.4.dist-info/entry_points.txt
git_security_scanner-0.1.4.dist-info/top_level.txt
git_security_scanner-0.1.4.dist-info/RECORD
