Metadata-Version: 2.4
Name: git-security-scanner
Version: 0.1.4
Summary: A comprehensive tool to detect secrets and sensitive information in Git repositories
Home-page: https://github.com/vyacheslavmeyerzon/security-scanner
Author: Vyacheslav Meyerzon
Author-email: Vyacheslav Meyerzon <vyacheslav.meyerzon@gmail.com>
License: MIT
Project-URL: Homepage, https://github.com/vyacheslavmeyerzon/security-scanner
Project-URL: Repository, https://github.com/vyacheslavmeyerzon/security-scanner
Project-URL: Issues, https://github.com/vyacheslavmeyerzon/security-scanner/issues
Project-URL: Documentation, https://github.com/vyacheslavmeyerzon/security-scanner/wiki
Keywords: security,git,secrets,scanner,api-keys,passwords,security-tools,devsecops,secret-detection,code-security
Classifier: Development Status :: 4 - Beta
Classifier: Intended Audience :: Developers
Classifier: Intended Audience :: System Administrators
Classifier: Topic :: Software Development :: Quality Assurance
Classifier: Topic :: Security
Classifier: Topic :: Software Development :: Version Control :: Git
Classifier: License :: OSI Approved :: MIT License
Classifier: Programming Language :: Python :: 3
Classifier: Programming Language :: Python :: 3.8
Classifier: Programming Language :: Python :: 3.9
Classifier: Programming Language :: Python :: 3.10
Classifier: Programming Language :: Python :: 3.11
Classifier: Programming Language :: Python :: 3.12
Classifier: Operating System :: OS Independent
Classifier: Environment :: Console
Requires-Python: >=3.8
License-File: LICENSE
Requires-Dist: colorama>=0.4.6
Requires-Dist: PyYAML>=6.0
Requires-Dist: tqdm>=4.65.0
Provides-Extra: dev
Requires-Dist: pytest>=7.0.0; extra == "dev"
Requires-Dist: pytest-cov>=4.0.0; extra == "dev"
Requires-Dist: pytest-mock>=3.10.0; extra == "dev"
Requires-Dist: black>=23.0.0; extra == "dev"
Requires-Dist: flake8>=6.0.0; extra == "dev"
Requires-Dist: mypy>=1.0.0; extra == "dev"
Requires-Dist: isort>=5.12.0; extra == "dev"
Requires-Dist: types-colorama>=0.4.15; extra == "dev"
Requires-Dist: types-PyYAML>=6.0; extra == "dev"
Requires-Dist: build>=0.10.0; extra == "dev"
Requires-Dist: twine>=4.0.2; extra == "dev"
Dynamic: author
Dynamic: home-page
Dynamic: license-file
Dynamic: requires-python
